analyzers/__init__.py
analyzers/docs.py
analyzers/naming.py
analyzers/source_file.py
exec/__init__.py
exec/main.py
util/__init__.py
util/util.py
Swift_CCF_Kravchuk-0.0.7.dist-info/LICENSE
Swift_CCF_Kravchuk-0.0.7.dist-info/METADATA
Swift_CCF_Kravchuk-0.0.7.dist-info/WHEEL
Swift_CCF_Kravchuk-0.0.7.dist-info/entry_points.txt
Swift_CCF_Kravchuk-0.0.7.dist-info/top_level.txt
Swift_CCF_Kravchuk-0.0.7.dist-info/RECORD
