Metadata-Version: 2.1
Name: Swift-CCF-Kravchuk
Version: 0.0.7
Summary: A swift code convention fixer
Home-page: https://github.com/Hybridlo/Metaprog
Author: Kravchuk Pavlo
Author-email: pashanoy@gmail.com
License: UNKNOWN
Platform: UNKNOWN
Classifier: Programming Language :: Python :: 3
Classifier: License :: OSI Approved :: MIT License
Classifier: Operating System :: OS Independent
Requires-Python: >=3.7
